veriloggen-develop/tmp.v


module simsort #
(
  parameter WIDTH = 32
)
(

);

  reg CLK;
  reg RST;
  reg [WIDTH-1:0] input_0;
  reg [WIDTH-1:0] input_1;
  reg [WIDTH-1:0] input_2;
  reg [WIDTH-1:0] input_3;
  wire [WIDTH-1:0] output_0;
  wire [WIDTH-1:0] output_1;
  wire [WIDTH-1:0] output_2;
  wire [WIDTH-1:0] output_3;
  reg kick;
  wire busy;

  sort
  #(
    .WIDTH(WIDTH)
  )
  uut
  (
    .CLK(CLK),
    .RST(RST),
    .input_0(input_0),
    .input_1(input_1),
    .input_2(input_2),
    .input_3(input_3),
    .output_0(output_0),
    .output_1(output_1),
    .output_2(output_2),
    .output_3(output_3),
    .kick(kick),
    .busy(busy)
  );


  initial begin
    $dumpfile("uut.vcd");
    $dumpvars(0, uut);
  end


  initial begin
    CLK = 0;
    forever begin
      #5 CLK = !CLK;
    end
  end


  initial begin
    RST = 0;
    #100;
    RST = 1;
    #100;
    RST = 0;
  end


  initial begin
    input_0 = 100;
    input_1 = 99;
    input_2 = 98;
    input_3 = 97;
    kick = 0;
    wait(RST);
    @(posedge CLK);
    #1;
    wait(!RST);
    @(posedge CLK);
    #1;
    @(posedge CLK);
    #1;
    @(posedge CLK);
    #1;
    kick = 1;
    @(posedge CLK);
    #1;
    kick = 0;
  end


  initial begin
    #100;
    wait(kick);
    @(posedge CLK);
    #1;
    wait(busy);
    @(posedge CLK);
    #1;
    wait(!busy);
    @(posedge CLK);
    #1;
    $finish;
  end


endmodule



module sort #
(
  parameter WIDTH = 32
)
(
  input CLK,
  input RST,
  input [WIDTH-1:0] input_0,
  input [WIDTH-1:0] input_1,
  input [WIDTH-1:0] input_2,
  input [WIDTH-1:0] input_3,
  output [WIDTH-1:0] output_0,
  output [WIDTH-1:0] output_1,
  output [WIDTH-1:0] output_2,
  output [WIDTH-1:0] output_3,
  input kick,
  output reg busy
);

  reg [WIDTH-1:0] registers_0;
  reg [WIDTH-1:0] registers_1;
  reg [WIDTH-1:0] registers_2;
  reg [WIDTH-1:0] registers_3;
  assign output_0 = registers_0;
  assign output_1 = registers_1;
  assign output_2 = registers_2;
  assign output_3 = registers_3;
  reg [32-1:0] fsm;
  localparam fsm_init = 0;
  wire [WIDTH-1:0] small_0;
  wire [WIDTH-1:0] large_0;
  assign small_0 = (registers_0 < registers_1)? registers_0 : registers_1;
  assign large_0 = (registers_0 < registers_1)? registers_1 : registers_0;
  wire [WIDTH-1:0] small_1;
  wire [WIDTH-1:0] large_1;
  assign small_1 = (large_0 < registers_2)? large_0 : registers_2;
  assign large_1 = (large_0 < registers_2)? registers_2 : large_0;
  wire [WIDTH-1:0] small_2;
  wire [WIDTH-1:0] large_2;
  assign small_2 = (large_1 < registers_3)? large_1 : registers_3;
  assign large_2 = (large_1 < registers_3)? registers_3 : large_1;
  wire [WIDTH-1:0] small_3;
  wire [WIDTH-1:0] large_3;
  assign small_3 = (registers_0 < registers_1)? registers_0 : registers_1;
  assign large_3 = (registers_0 < registers_1)? registers_1 : registers_0;
  wire [WIDTH-1:0] small_4;
  wire [WIDTH-1:0] large_4;
  assign small_4 = (large_3 < registers_2)? large_3 : registers_2;
  assign large_4 = (large_3 < registers_2)? registers_2 : large_3;
  wire [WIDTH-1:0] small_5;
  wire [WIDTH-1:0] large_5;
  assign small_5 = (registers_0 < registers_1)? registers_0 : registers_1;
  assign large_5 = (registers_0 < registers_1)? registers_1 : registers_0;
  localparam fsm_1 = 1;
  localparam fsm_2 = 2;
  localparam fsm_3 = 3;
  localparam fsm_4 = 4;
  localparam fsm_5 = 5;

  always @(posedge CLK) begin
    if(RST) begin
      busy <= 0;
      registers_0 <= 0;
      registers_1 <= 0;
      registers_2 <= 0;
      registers_3 <= 0;
      fsm <= fsm_init;
    end else begin
      $display("registers_0: %d", registers_0);
      $display("registers_1: %d", registers_1);
      $display("registers_2: %d", registers_2);
      $display("registers_3: %d", registers_3);
      case(fsm)
        fsm_init: begin
          if(kick) begin
            registers_0 <= input_0;
            registers_1 <= input_1;
            registers_2 <= input_2;
            registers_3 <= input_3;
          end 
          if(kick) begin
            busy <= 1;
          end 
          if(kick) begin
            fsm <= fsm_1;
          end 
        end
        fsm_1: begin
          registers_0 <= small_0;
          registers_1 <= small_1;
          registers_2 <= small_2;
          registers_3 <= large_2;
          fsm <= fsm_2;
        end
        fsm_2: begin
          registers_0 <= small_3;
          registers_1 <= small_4;
          registers_2 <= large_4;
          registers_3 <= registers_3;
          fsm <= fsm_3;
        end
        fsm_3: begin
          registers_0 <= small_5;
          registers_1 <= large_5;
          registers_2 <= registers_2;
          registers_3 <= registers_3;
          fsm <= fsm_4;
        end
        fsm_4: begin
          registers_0 <= registers_0;
          registers_1 <= registers_1;
          registers_2 <= registers_2;
          registers_3 <= registers_3;
          fsm <= fsm_5;
        end
        fsm_5: begin
          busy <= 0;
          fsm <= fsm_init;
        end
      endcase
    end
  end


endmodule

veriloggen-develop/examples/sort/uut.vcd
$date
	Thu Jun 17 14:29:52 2021
$end
$version
	Icarus Verilog
$end
$timescale
	1s
$end
$scope module simsort $end
$scope module uut $end
$var wire 1 ! CLK $end
$var wire 1 " RST $end
$var wire 32 # input_0 [31:0] $end
$var wire 32 $ input_1 [31:0] $end
$var wire 32 % input_2 [31:0] $end
$var wire 32 & input_3 [31:0] $end
$var wire 1 ' kick $end
$var wire 32 ( output_0 [31:0] $end
$var wire 32 ) output_1 [31:0] $end
$var wire 32 * output_2 [31:0] $end
$var wire 32 + output_3 [31:0] $end
$var wire 32 , small_5 [31:0] $end
$var wire 32 - small_4 [31:0] $end
$var wire 32 . small_3 [31:0] $end
$var wire 32 / small_2 [31:0] $end
$var wire 32 0 small_1 [31:0] $end
$var wire 32 1 small_0 [31:0] $end
$var wire 32 2 large_5 [31:0] $end
$var wire 32 3 large_4 [31:0] $end
$var wire 32 4 large_3 [31:0] $end
$var wire 32 5 large_2 [31:0] $end
$var wire 32 6 large_1 [31:0] $end
$var wire 32 7 large_0 [31:0] $end
$var reg 1 8 busy $end
$var reg 32 9 fsm [31:0] $end
$var reg 32 : registers_0 [31:0] $end
$var reg 32 ; registers_1 [31:0] $end
$var reg 32 < registers_2 [31:0] $end
$var reg 32 = registers_3 [31:0] $end
$upscope $end
$upscope $end
$enddefinitions $end
#0
$dumpvars
bx =
bx <
bx ;
bx :
bx 9
x8
bx 7
bx 6
bx 5
bx 4
bx 3
bx 2
bx 1
bx 0
bx /
bx .
bx -
bx ,
bx +
bx *
bx )
bx (
0'
b1100001 &
b1100010 %
b1100011 $
b1100100 #
0"
0!
$end
#5
1!
#10
0!
#15
1!
#20
0!
#25
1!
#30
0!
#35
1!
#40
0!
#45
1!
#50
0!
#55
1!
#60
0!
#65
1!
#70
0!
#75
1!
#80
0!
#85
1!
#90
0!
#95
1!
#100
0!
1"
#105
b0 /
b0 5
b0 0
b0 6
b0 -
b0 3
b0 1
b0 7
b0 .
b0 4
b0 ,
b0 2
b0 9
b0 +
b0 =
b0 *
b0 <
b0 )
b0 ;
b0 (
b0 :
08
1!
#110
0!
#115
1!
#120
0!
#125
1!
#130
0!
#135
1!
#140
0!
#145
1!
#150
0!
#155
1!
#160
0!
#165
1!
#170
0!
#175
1!
#180
0!
#185
1!
#190
0!
#195
1!
#200
0!
0"
#205
1!
#210
0!
#215
1!
#220
0!
#225
1!
#226
1'
#230
0!
#235
b1100001 /
b1100100 5
b1100010 0
b1100100 6
b1100010 -
b1100100 3
b1100011 1
b1100011 .
b1100011 ,
b1100100 7
b1100100 4
b1100100 2
b1 9
18
b1100001 +
b1100001 =
b1100010 *
b1100010 <
b1100011 )
b1100011 ;
b1100100 (
b1100100 :
1!
#236
0'
#240
0!
#245
b1100011 6
b1100011 3
b1100011 /
b1100001 0
b1100001 -
b1100010 1
b1100010 .
b1100010 ,
b1100011 7
b1100011 4
b1100011 2
b10 9
b1100100 +
b1100100 =
b1100001 *
b1100001 <
b1100010 )
b1100010 ;
b1100011 (
b1100011 :
1!
#250
0!
#255
b1100010 0
b1100010 -
b1100001 1
b1100001 .
b1100001 ,
b1100010 7
b1100010 4
b1100010 2
b11 9
b1100011 *
b1100011 <
b1100001 )
b1100001 ;
b1100010 (
b1100010 :
1!
#260
0!
#265
b100 9
b1100010 )
b1100010 ;
b1100001 (
b1100001 :
1!
#270
0!
#275
b101 9
1!
#280
0!
#285
b0 9
08
1!
