veriloggen-develop/examples/fifo_rtl/tmp.v


module test
(

);

  reg CLK;
  reg RST;

  main
  uut
  (
    .CLK(CLK),
    .RST(RST)
  );


  initial begin
    $dumpfile("uut.vcd");
    $dumpvars(0, uut, CLK, RST);
  end


  initial begin
    CLK = 0;
    forever begin
      #5 CLK = !CLK;
    end
  end


  initial begin
    RST = 0;
    #100;
    RST = 1;
    #100;
    RST = 0;
    #100000;
    $finish;
  end


endmodule



module main
(
  input CLK,
  input RST
);

  wire myfifo_enq;
  wire [32-1:0] myfifo_wdata;
  wire myfifo_full;
  wire myfifo_almost_full;
  wire myfifo_deq;
  wire [32-1:0] myfifo_rdata;
  wire myfifo_empty;
  wire myfifo_almost_empty;

  myfifo
  inst_myfifo
  (
    .CLK(CLK),
    .RST(RST),
    .myfifo_enq(myfifo_enq),
    .myfifo_wdata(myfifo_wdata),
    .myfifo_full(myfifo_full),
    .myfifo_almost_full(myfifo_almost_full),
    .myfifo_deq(myfifo_deq),
    .myfifo_rdata(myfifo_rdata),
    .myfifo_empty(myfifo_empty),
    .myfifo_almost_empty(myfifo_almost_empty)
  );

  reg [8-1:0] count_myfifo;
  reg [32-1:0] count;
  reg [32-1:0] sum;
  reg [32-1:0] fsm;
  localparam fsm_init = 0;
  assign myfifo_wdata = (fsm == 1)? count : 'hx;
  assign myfifo_enq = (fsm == 1)? (fsm == 1) && !myfifo_almost_full : 0;
  localparam _tmp_0 = 1;
  wire [_tmp_0-1:0] _tmp_1;
  assign _tmp_1 = !myfifo_almost_full;
  reg [_tmp_0-1:0] __tmp_1_1;
  assign myfifo_deq = ((fsm == 3) && !myfifo_empty)? 1 : 0;
  localparam _tmp_2 = 1;
  wire [_tmp_2-1:0] _tmp_3;
  assign _tmp_3 = (fsm == 3) && !myfifo_empty;
  reg [_tmp_2-1:0] __tmp_3_1;
  reg [32-1:0] _d1_fsm;
  reg _fsm_cond_3_0_1;
  localparam fsm_1 = 1;
  localparam fsm_2 = 2;
  localparam fsm_3 = 3;
  localparam fsm_4 = 4;
  localparam fsm_5 = 5;

  always @(posedge CLK) begin
    if(RST) begin
      fsm <= fsm_init;
      _d1_fsm <= fsm_init;
      count <= 0;
      sum <= 0;
      _fsm_cond_3_0_1 <= 0;
    end else begin
      _d1_fsm <= fsm;
      case(_d1_fsm)
        fsm_3: begin
          if(_fsm_cond_3_0_1) begin
            $display("sum=%d", sum);
          end 
        end
      endcase
      case(fsm)
        fsm_init: begin
          count <= 0;
          fsm <= fsm_1;
        end
        fsm_1: begin
          if(!myfifo_almost_full) begin
            count <= count + 1;
          end 
          if(__tmp_1_1) begin
            $display("count=%d space=%d has_space=%d", count_myfifo, (127 - count_myfifo), (count_myfifo + 1 < 127));
          end 
          if(!myfifo_almost_full && (count == 125)) begin
            fsm <= fsm_2;
          end 
        end
        fsm_2: begin
          count <= 0;
          fsm <= fsm_3;
        end
        fsm_3: begin
          if(__tmp_3_1) begin
            sum <= sum + myfifo_rdata;
            count <= count + 1;
            $write("count=%d space=%d has_space=%d ", count_myfifo, (127 - count_myfifo), (count_myfifo + 1 < 127));
          end 
          _fsm_cond_3_0_1 <= __tmp_3_1;
          if(count == 126) begin
            fsm <= fsm_4;
          end 
        end
        fsm_4: begin
          $display("expected_sum=%d", 7875);
          fsm <= fsm_5;
        end
      endcase
    end
  end


  always @(posedge CLK) begin
    if(RST) begin
      count_myfifo <= 0;
      __tmp_1_1 <= 0;
      __tmp_3_1 <= 0;
    end else begin
      if(myfifo_enq && !myfifo_full && (myfifo_deq && !myfifo_empty)) begin
        count_myfifo <= count_myfifo;
      end else if(myfifo_enq && !myfifo_full) begin
        count_myfifo <= count_myfifo + 1;
      end else if(myfifo_deq && !myfifo_empty) begin
        count_myfifo <= count_myfifo - 1;
      end 
      __tmp_1_1 <= _tmp_1;
      __tmp_3_1 <= _tmp_3;
    end
  end


endmodule



module myfifo
(
  input CLK,
  input RST,
  input myfifo_enq,
  input [32-1:0] myfifo_wdata,
  output myfifo_full,
  output myfifo_almost_full,
  input myfifo_deq,
  output [32-1:0] myfifo_rdata,
  output myfifo_empty,
  output myfifo_almost_empty
);

  reg [32-1:0] mem [0:128-1];
  reg [7-1:0] head;
  reg [7-1:0] tail;
  wire is_empty;
  wire is_almost_empty;
  wire is_full;
  wire is_almost_full;
  assign is_empty = head == tail;
  assign is_almost_empty = head == (tail + 1 & 127);
  assign is_full = (head + 1 & 127) == tail;
  assign is_almost_full = (head + 2 & 127) == tail;
  reg [32-1:0] rdata_reg;
  assign myfifo_full = is_full;
  assign myfifo_almost_full = is_almost_full || is_full;
  assign myfifo_empty = is_empty;
  assign myfifo_almost_empty = is_almost_empty || is_empty;
  assign myfifo_rdata = rdata_reg;

  always @(posedge CLK) begin
    if(RST) begin
      head <= 0;
      rdata_reg <= 0;
      tail <= 0;
    end else begin
      if(myfifo_enq && !is_full) begin
        mem[head] <= myfifo_wdata;
        head <= head + 1;
      end 
      if(myfifo_deq && !is_empty) begin
        rdata_reg <= mem[tail];
        tail <= tail + 1;
      end 
    end
  end


endmodule

veriloggen-develop/examples/fifo_rtl/uut.vcd
$date
	Sat Jun 19 21:36:46 2021
$end
$version
	Icarus Verilog
$end
$timescale
	1s
$end
$scope module test $end
$scope module uut $end
$var wire 1 ! CLK $end
$var wire 1 " RST $end
$var wire 1 # _tmp_3 $end
$var wire 32 $ myfifo_wdata [31:0] $end
$var wire 32 % myfifo_rdata [31:0] $end
$var wire 1 & myfifo_full $end
$var wire 1 ' myfifo_enq $end
$var wire 1 ( myfifo_empty $end
$var wire 1 ) myfifo_deq $end
$var wire 1 * myfifo_almost_full $end
$var wire 1 + myfifo_almost_empty $end
$var wire 1 , _tmp_1 $end
$var reg 1 - __tmp_1_1 $end
$var reg 1 . __tmp_3_1 $end
$var reg 32 / _d1_fsm [31:0] $end
$var reg 1 0 _fsm_cond_3_0_1 $end
$var reg 32 1 count [31:0] $end
$var reg 8 2 count_myfifo [7:0] $end
$var reg 32 3 fsm [31:0] $end
$var reg 32 4 sum [31:0] $end
$scope module inst_myfifo $end
$var wire 1 ! CLK $end
$var wire 1 " RST $end
$var wire 1 + myfifo_almost_empty $end
$var wire 1 * myfifo_almost_full $end
$var wire 1 ) myfifo_deq $end
$var wire 1 ( myfifo_empty $end
$var wire 1 ' myfifo_enq $end
$var wire 1 & myfifo_full $end
$var wire 32 5 myfifo_rdata [31:0] $end
$var wire 32 6 myfifo_wdata [31:0] $end
$var wire 1 7 is_full $end
$var wire 1 8 is_empty $end
$var wire 1 9 is_almost_full $end
$var wire 1 : is_almost_empty $end
$var reg 7 ; head [6:0] $end
$var reg 32 < rdata_reg [31:0] $end
$var reg 7 = tail [6:0] $end
$upscope $end
$upscope $end
$upscope $end
$scope module test $end
$var reg 1 ! CLK $end
$upscope $end
$scope module test $end
$var reg 1 " RST $end
$upscope $end
$enddefinitions $end
#0
$dumpvars
bx =
bx <
bx ;
x:
x9
x8
x7
bx 6
bx 5
bx 4
bx 3
bx 2
bx 1
x0
bx /
x.
x-
x,
x+
x*
x)
x(
x'
x&
bx %
bx $
x#
0"
0!
$end
#5
1!
#10
0!
#15
1!
#20
0!
#25
1!
#30
0!
#35
1!
#40
0!
#45
1!
#50
0!
#55
1!
#60
0!
#65
1!
#70
0!
#75
1!
#80
0!
#85
1!
#90
0!
#95
1!
#100
0!
1"
#105
0)
1,
0*
1+
0:
0&
07
09
0'
0#
1(
18
b0 =
b0 %
b0 5
b0 <
b0 ;
00
b0 4
b0 1
b0 /
b0 3
0.
0-
b0 2
1!
#110
0!
#115
1!
#120
0!
#125
1!
#130
0!
#135
1!
#140
0!
#145
1!
#150
0!
#155
1!
#160
0!
#165
1!
#170
0!
#175
1!
#180
0!
#185
1!
#190
0!
#195
1!
#200
0!
0"
#205
b0 $
b0 6
1'
b1 3
1-
1!
#210
0!
#215
b1 $
b1 6
b1 2
b1 1
b1 /
0(
08
1:
b1 ;
1!
#220
0!
#225
0+
b10 $
b10 6
0:
b10 ;
b10 1
b10 2
1!
#230
0!
#235
b11 $
b11 6
b11 2
b11 1
b11 ;
1!
#240
0!
#245
b100 $
b100 6
b100 ;
b100 1
b100 2
1!
#250
0!
#255
b101 $
b101 6
b101 2
b101 1
b101 ;
1!
#260
0!
#265
b110 $
b110 6
b110 ;
b110 1
b110 2
1!
#270
0!
#275
b111 $
b111 6
b111 2
b111 1
b111 ;
1!
#280
0!
#285
b1000 $
b1000 6
b1000 ;
b1000 1
b1000 2
1!
#290
0!
#295
b1001 $
b1001 6
b1001 2
b1001 1
b1001 ;
1!
#300
0!
#305
b1010 $
b1010 6
b1010 ;
b1010 1
b1010 2
1!
#310
0!
#315
b1011 $
b1011 6
b1011 2
b1011 1
b1011 ;
1!
#320
0!
#325
b1100 $
b1100 6
b1100 ;
b1100 1
b1100 2
1!
#330
0!
#335
b1101 $
b1101 6
b1101 2
b1101 1
b1101 ;
1!
#340
0!
#345
b1110 $
b1110 6
b1110 ;
b1110 1
b1110 2
1!
#350
0!
#355
b1111 $
b1111 6
b1111 2
b1111 1
b1111 ;
1!
#360
0!
#365
b10000 $
b10000 6
b10000 ;
b10000 1
b10000 2
1!
#370
0!
#375
b10001 $
b10001 6
b10001 2
b10001 1
b10001 ;
1!
#380
0!
#385
b10010 $
b10010 6
b10010 ;
b10010 1
b10010 2
1!
#390
0!
#395
b10011 $
b10011 6
b10011 2
b10011 1
b10011 ;
1!
#400
0!
#405
b10100 $
b10100 6
b10100 ;
b10100 1
b10100 2
1!
#410
0!
#415
b10101 $
b10101 6
b10101 2
b10101 1
b10101 ;
1!
#420
0!
#425
b10110 $
b10110 6
b10110 ;
b10110 1
b10110 2
1!
#430
0!
#435
b10111 $
b10111 6
b10111 2
b10111 1
b10111 ;
1!
#440
0!
#445
b11000 $
b11000 6
b11000 ;
b11000 1
b11000 2
1!
#450
0!
#455
b11001 $
b11001 6
b11001 2
b11001 1
b11001 ;
1!
#460
0!
#465
b11010 $
b11010 6
b11010 ;
b11010 1
b11010 2
1!
#470
0!
#475
b11011 $
b11011 6
b11011 2
b11011 1
b11011 ;
1!
#480
0!
#485
b11100 $
b11100 6
b11100 ;
b11100 1
b11100 2
1!
#490
0!
#495
b11101 $
b11101 6
b11101 2
b11101 1
b11101 ;
1!
#500
0!
#505
b11110 $
b11110 6
b11110 ;
b11110 1
b11110 2
1!
#510
0!
#515
b11111 $
b11111 6
b11111 2
b11111 1
b11111 ;
1!
#520
0!
#525
b100000 $
b100000 6
b100000 ;
b100000 1
b100000 2
1!
#530
0!
#535
b100001 $
b100001 6
b100001 2
b100001 1
b100001 ;
1!
#540
0!
#545
b100010 $
b100010 6
b100010 ;
b100010 1
b100010 2
1!
#550
0!
#555
b100011 $
b100011 6
b100011 2
b100011 1
b100011 ;
1!
#560
0!
#565
b100100 $
b100100 6
b100100 ;
b100100 1
b100100 2
1!
#570
0!
#575
b100101 $
b100101 6
b100101 2
b100101 1
b100101 ;
1!
#580
0!
#585
b100110 $
b100110 6
b100110 ;
b100110 1
b100110 2
1!
#590
0!
#595
b100111 $
b100111 6
b100111 2
b100111 1
b100111 ;
1!
#600
0!
#605
b101000 $
b101000 6
b101000 ;
b101000 1
b101000 2
1!
#610
0!
#615
b101001 $
b101001 6
b101001 2
b101001 1
b101001 ;
1!
#620
0!
#625
b101010 $
b101010 6
b101010 ;
b101010 1
b101010 2
1!
#630
0!
#635
b101011 $
b101011 6
b101011 2
b101011 1
b101011 ;
1!
#640
0!
#645
b101100 $
b101100 6
b101100 ;
b101100 1
b101100 2
1!
#650
0!
#655
b101101 $
b101101 6
b101101 2
b101101 1
b101101 ;
1!
#660
0!
#665
b101110 $
b101110 6
b101110 ;
b101110 1
b101110 2
1!
#670
0!
#675
b101111 $
b101111 6
b101111 2
b101111 1
b101111 ;
1!
#680
0!
#685
b110000 $
b110000 6
b110000 ;
b110000 1
b110000 2
1!
#690
0!
#695
b110001 $
b110001 6
b110001 2
b110001 1
b110001 ;
1!
#700
0!
#705
b110010 $
b110010 6
b110010 ;
b110010 1
b110010 2
1!
#710
0!
#715
b110011 $
b110011 6
b110011 2
b110011 1
b110011 ;
1!
#720
0!
#725
b110100 $
b110100 6
b110100 ;
b110100 1
b110100 2
1!
#730
0!
#735
b110101 $
b110101 6
b110101 2
b110101 1
b110101 ;
1!
#740
0!
#745
b110110 $
b110110 6
b110110 ;
b110110 1
b110110 2
1!
#750
0!
#755
b110111 $
b110111 6
b110111 2
b110111 1
b110111 ;
1!
#760
0!
#765
b111000 $
b111000 6
b111000 ;
b111000 1
b111000 2
1!
#770
0!
#775
b111001 $
b111001 6
b111001 2
b111001 1
b111001 ;
1!
#780
0!
#785
b111010 $
b111010 6
b111010 ;
b111010 1
b111010 2
1!
#790
0!
#795
b111011 $
b111011 6
b111011 2
b111011 1
b111011 ;
1!
#800
0!
#805
b111100 $
b111100 6
b111100 ;
b111100 1
b111100 2
1!
#810
0!
#815
b111101 $
b111101 6
b111101 2
b111101 1
b111101 ;
1!
#820
0!
#825
b111110 $
b111110 6
b111110 ;
b111110 1
b111110 2
1!
#830
0!
#835
b111111 $
b111111 6
b111111 2
b111111 1
b111111 ;
1!
#840
0!
#845
b1000000 $
b1000000 6
b1000000 ;
b1000000 1
b1000000 2
1!
#850
0!
#855
b1000001 $
b1000001 6
b1000001 2
b1000001 1
b1000001 ;
1!
#860
0!
#865
b1000010 $
b1000010 6
b1000010 ;
b1000010 1
b1000010 2
1!
#870
0!
#875
b1000011 $
b1000011 6
b1000011 2
b1000011 1
b1000011 ;
1!
#880
0!
#885
b1000100 $
b1000100 6
b1000100 ;
b1000100 1
b1000100 2
1!
#890
0!
#895
b1000101 $
b1000101 6
b1000101 2
b1000101 1
b1000101 ;
1!
#900
0!
#905
b1000110 $
b1000110 6
b1000110 ;
b1000110 1
b1000110 2
1!
#910
0!
#915
b1000111 $
b1000111 6
b1000111 2
b1000111 1
b1000111 ;
1!
#920
0!
#925
b1001000 $
b1001000 6
b1001000 ;
b1001000 1
b1001000 2
1!
#930
0!
#935
b1001001 $
b1001001 6
b1001001 2
b1001001 1
b1001001 ;
1!
#940
0!
#945
b1001010 $
b1001010 6
b1001010 ;
b1001010 1
b1001010 2
1!
#950
0!
#955
b1001011 $
b1001011 6
b1001011 2
b1001011 1
b1001011 ;
1!
#960
0!
#965
b1001100 $
b1001100 6
b1001100 ;
b1001100 1
b1001100 2
1!
#970
0!
#975
b1001101 $
b1001101 6
b1001101 2
b1001101 1
b1001101 ;
1!
#980
0!
#985
b1001110 $
b1001110 6
b1001110 ;
b1001110 1
b1001110 2
1!
#990
0!
#995
b1001111 $
b1001111 6
b1001111 2
b1001111 1
b1001111 ;
1!
#1000
0!
#1005
b1010000 $
b1010000 6
b1010000 ;
b1010000 1
b1010000 2
1!
#1010
0!
#1015
b1010001 $
b1010001 6
b1010001 2
b1010001 1
b1010001 ;
1!
#1020
0!
#1025
b1010010 $
b1010010 6
b1010010 ;
b1010010 1
b1010010 2
1!
#1030
0!
#1035
b1010011 $
b1010011 6
b1010011 2
b1010011 1
b1010011 ;
1!
#1040
0!
#1045
b1010100 $
b1010100 6
b1010100 ;
b1010100 1
b1010100 2
1!
#1050
0!
#1055
b1010101 $
b1010101 6
b1010101 2
b1010101 1
b1010101 ;
1!
#1060
0!
#1065
b1010110 $
b1010110 6
b1010110 ;
b1010110 1
b1010110 2
1!
#1070
0!
#1075
b1010111 $
b1010111 6
b1010111 2
b1010111 1
b1010111 ;
1!
#1080
0!
#1085
b1011000 $
b1011000 6
b1011000 ;
b1011000 1
b1011000 2
1!
#1090
0!
#1095
b1011001 $
b1011001 6
b1011001 2
b1011001 1
b1011001 ;
1!
#1100
0!
#1105
b1011010 $
b1011010 6
b1011010 ;
b1011010 1
b1011010 2
1!
#1110
0!
#1115
b1011011 $
b1011011 6
b1011011 2
b1011011 1
b1011011 ;
1!
#1120
0!
#1125
b1011100 $
b1011100 6
b1011100 ;
b1011100 1
b1011100 2
1!
#1130
0!
#1135
b1011101 $
b1011101 6
b1011101 2
b1011101 1
b1011101 ;
1!
#1140
0!
#1145
b1011110 $
b1011110 6
b1011110 ;
b1011110 1
b1011110 2
1!
#1150
0!
#1155
b1011111 $
b1011111 6
b1011111 2
b1011111 1
b1011111 ;
1!
#1160
0!
#1165
b1100000 $
b1100000 6
b1100000 ;
b1100000 1
b1100000 2
1!
#1170
0!
#1175
b1100001 $
b1100001 6
b1100001 2
b1100001 1
b1100001 ;
1!
#1180
0!
#1185
b1100010 $
b1100010 6
b1100010 ;
b1100010 1
b1100010 2
1!
#1190
0!
#1195
b1100011 $
b1100011 6
b1100011 2
b1100011 1
b1100011 ;
1!
#1200
0!
#1205
b1100100 $
b1100100 6
b1100100 ;
b1100100 1
b1100100 2
1!
#1210
0!
#1215
b1100101 $
b1100101 6
b1100101 2
b1100101 1
b1100101 ;
1!
#1220
0!
#1225
b1100110 $
b1100110 6
b1100110 ;
b1100110 1
b1100110 2
1!
#1230
0!
#1235
b1100111 $
b1100111 6
b1100111 2
b1100111 1
b1100111 ;
1!
#1240
0!
#1245
b1101000 $
b1101000 6
b1101000 ;
b1101000 1
b1101000 2
1!
#1250
0!
#1255
b1101001 $
b1101001 6
b1101001 2
b1101001 1
b1101001 ;
1!
#1260
0!
#1265
b1101010 $
b1101010 6
b1101010 ;
b1101010 1
b1101010 2
1!
#1270
0!
#1275
b1101011 $
b1101011 6
b1101011 2
b1101011 1
b1101011 ;
1!
#1280
0!
#1285
b1101100 $
b1101100 6
b1101100 ;
b1101100 1
b1101100 2
1!
#1290
0!
#1295
b1101101 $
b1101101 6
b1101101 2
b1101101 1
b1101101 ;
1!
#1300
0!
#1305
b1101110 $
b1101110 6
b1101110 ;
b1101110 1
b1101110 2
1!
#1310
0!
#1315
b1101111 $
b1101111 6
b1101111 2
b1101111 1
b1101111 ;
1!
#1320
0!
#1325
b1110000 $
b1110000 6
b1110000 ;
b1110000 1
b1110000 2
1!
#1330
0!
#1335
b1110001 $
b1110001 6
b1110001 2
b1110001 1
b1110001 ;
1!
#1340
0!
#1345
b1110010 $
b1110010 6
b1110010 ;
b1110010 1
b1110010 2
1!
#1350
0!
#1355
b1110011 $
b1110011 6
b1110011 2
b1110011 1
b1110011 ;
1!
#1360
0!
#1365
b1110100 $
b1110100 6
b1110100 ;
b1110100 1
b1110100 2
1!
#1370
0!
#1375
b1110101 $
b1110101 6
b1110101 2
b1110101 1
b1110101 ;
1!
#1380
0!
#1385
b1110110 $
b1110110 6
b1110110 ;
b1110110 1
b1110110 2
1!
#1390
0!
#1395
b1110111 $
b1110111 6
b1110111 2
b1110111 1
b1110111 ;
1!
#1400
0!
#1405
b1111000 $
b1111000 6
b1111000 ;
b1111000 1
b1111000 2
1!
#1410
0!
#1415
b1111001 $
b1111001 6
b1111001 2
b1111001 1
b1111001 ;
1!
#1420
0!
#1425
b1111010 $
b1111010 6
b1111010 ;
b1111010 1
b1111010 2
1!
#1430
0!
#1435
b1111011 $
b1111011 6
b1111011 2
b1111011 1
b1111011 ;
1!
#1440
0!
#1445
b1111100 $
b1111100 6
b1111100 ;
b1111100 1
b1111100 2
1!
#1450
0!
#1455
b1111101 $
b1111101 6
b1111101 2
b1111101 1
b1111101 ;
1!
#1460
0!
#1465
0,
1*
19
0'
bx $
bx 6
b1111110 ;
b10 3
b1111110 1
b1111110 2
1!
#1470
0!
#1475
1)
1#
0-
b11 3
b0 1
b10 /
1!
#1480
0!
#1485
1,
0*
09
b1 =
b11 /
1.
b1111101 2
1!
#1490
0!
#1495
1-
b1111100 2
10
b1 1
b10 =
b1 %
b1 5
b1 <
1!
#1500
0!
#1505
b11 =
b10 %
b10 5
b10 <
b10 1
b1 4
b1111011 2
1!
#1510
0!
#1515
b1111010 2
b11 1
b11 4
b100 =
b11 %
b11 5
b11 <
1!
#1520
0!
#1525
b101 =
b100 %
b100 5
b100 <
b100 1
b110 4
b1111001 2
1!
#1530
0!
#1535
b1111000 2
b101 1
b1010 4
b110 =
b101 %
b101 5
b101 <
1!
#1540
0!
#1545
b111 =
b110 %
b110 5
b110 <
b110 1
b1111 4
b1110111 2
1!
#1550
0!
#1555
b1110110 2
b111 1
b10101 4
b1000 =
b111 %
b111 5
b111 <
1!
#1560
0!
#1565
b1001 =
b1000 %
b1000 5
b1000 <
b1000 1
b11100 4
b1110101 2
1!
#1570
0!
#1575
b1110100 2
b1001 1
b100100 4
b1010 =
b1001 %
b1001 5
b1001 <
1!
#1580
0!
#1585
b1011 =
b1010 %
b1010 5
b1010 <
b1010 1
b101101 4
b1110011 2
1!
#1590
0!
#1595
b1110010 2
b1011 1
b110111 4
b1100 =
b1011 %
b1011 5
b1011 <
1!
#1600
0!
#1605
b1101 =
b1100 %
b1100 5
b1100 <
b1100 1
b1000010 4
b1110001 2
1!
#1610
0!
#1615
b1110000 2
b1101 1
b1001110 4
b1110 =
b1101 %
b1101 5
b1101 <
1!
#1620
0!
#1625
b1111 =
b1110 %
b1110 5
b1110 <
b1110 1
b1011011 4
b1101111 2
1!
#1630
0!
#1635
b1101110 2
b1111 1
b1101001 4
b10000 =
b1111 %
b1111 5
b1111 <
1!
#1640
0!
#1645
b10001 =
b10000 %
b10000 5
b10000 <
b10000 1
b1111000 4
b1101101 2
1!
#1650
0!
#1655
b1101100 2
b10001 1
b10001000 4
b10010 =
b10001 %
b10001 5
b10001 <
1!
#1660
0!
#1665
b10011 =
b10010 %
b10010 5
b10010 <
b10010 1
b10011001 4
b1101011 2
1!
#1670
0!
#1675
b1101010 2
b10011 1
b10101011 4
b10100 =
b10011 %
b10011 5
b10011 <
1!
#1680
0!
#1685
b10101 =
b10100 %
b10100 5
b10100 <
b10100 1
b10111110 4
b1101001 2
1!
#1690
0!
#1695
b1101000 2
b10101 1
b11010010 4
b10110 =
b10101 %
b10101 5
b10101 <
1!
#1700
0!
#1705
b10111 =
b10110 %
b10110 5
b10110 <
b10110 1
b11100111 4
b1100111 2
1!
#1710
0!
#1715
b1100110 2
b10111 1
b11111101 4
b11000 =
b10111 %
b10111 5
b10111 <
1!
#1720
0!
#1725
b11001 =
b11000 %
b11000 5
b11000 <
b11000 1
b100010100 4
b1100101 2
1!
#1730
0!
#1735
b1100100 2
b11001 1
b100101100 4
b11010 =
b11001 %
b11001 5
b11001 <
1!
#1740
0!
#1745
b11011 =
b11010 %
b11010 5
b11010 <
b11010 1
b101000101 4
b1100011 2
1!
#1750
0!
#1755
b1100010 2
b11011 1
b101011111 4
b11100 =
b11011 %
b11011 5
b11011 <
1!
#1760
0!
#1765
b11101 =
b11100 %
b11100 5
b11100 <
b11100 1
b101111010 4
b1100001 2
1!
#1770
0!
#1775
b1100000 2
b11101 1
b110010110 4
b11110 =
b11101 %
b11101 5
b11101 <
1!
#1780
0!
#1785
b11111 =
b11110 %
b11110 5
b11110 <
b11110 1
b110110011 4
b1011111 2
1!
#1790
0!
#1795
b1011110 2
b11111 1
b111010001 4
b100000 =
b11111 %
b11111 5
b11111 <
1!
#1800
0!
#1805
b100001 =
b100000 %
b100000 5
b100000 <
b100000 1
b111110000 4
b1011101 2
1!
#1810
0!
#1815
b1011100 2
b100001 1
b1000010000 4
b100010 =
b100001 %
b100001 5
b100001 <
1!
#1820
0!
#1825
b100011 =
b100010 %
b100010 5
b100010 <
b100010 1
b1000110001 4
b1011011 2
1!
#1830
0!
#1835
b1011010 2
b100011 1
b1001010011 4
b100100 =
b100011 %
b100011 5
b100011 <
1!
#1840
0!
#1845
b100101 =
b100100 %
b100100 5
b100100 <
b100100 1
b1001110110 4
b1011001 2
1!
#1850
0!
#1855
b1011000 2
b100101 1
b1010011010 4
b100110 =
b100101 %
b100101 5
b100101 <
1!
#1860
0!
#1865
b100111 =
b100110 %
b100110 5
b100110 <
b100110 1
b1010111111 4
b1010111 2
1!
#1870
0!
#1875
b1010110 2
b100111 1
b1011100101 4
b101000 =
b100111 %
b100111 5
b100111 <
1!
#1880
0!
#1885
b101001 =
b101000 %
b101000 5
b101000 <
b101000 1
b1100001100 4
b1010101 2
1!
#1890
0!
#1895
b1010100 2
b101001 1
b1100110100 4
b101010 =
b101001 %
b101001 5
b101001 <
1!
#1900
0!
#1905
b101011 =
b101010 %
b101010 5
b101010 <
b101010 1
b1101011101 4
b1010011 2
1!
#1910
0!
#1915
b1010010 2
b101011 1
b1110000111 4
b101100 =
b101011 %
b101011 5
b101011 <
1!
#1920
0!
#1925
b101101 =
b101100 %
b101100 5
b101100 <
b101100 1
b1110110010 4
b1010001 2
1!
#1930
0!
#1935
b1010000 2
b101101 1
b1111011110 4
b101110 =
b101101 %
b101101 5
b101101 <
1!
#1940
0!
#1945
b101111 =
b101110 %
b101110 5
b101110 <
b101110 1
b10000001011 4
b1001111 2
1!
#1950
0!
#1955
b1001110 2
b101111 1
b10000111001 4
b110000 =
b101111 %
b101111 5
b101111 <
1!
#1960
0!
#1965
b110001 =
b110000 %
b110000 5
b110000 <
b110000 1
b10001101000 4
b1001101 2
1!
#1970
0!
#1975
b1001100 2
b110001 1
b10010011000 4
b110010 =
b110001 %
b110001 5
b110001 <
1!
#1980
0!
#1985
b110011 =
b110010 %
b110010 5
b110010 <
b110010 1
b10011001001 4
b1001011 2
1!
#1990
0!
#1995
b1001010 2
b110011 1
b10011111011 4
b110100 =
b110011 %
b110011 5
b110011 <
1!
#2000
0!
#2005
b110101 =
b110100 %
b110100 5
b110100 <
b110100 1
b10100101110 4
b1001001 2
1!
#2010
0!
#2015
b1001000 2
b110101 1
b10101100010 4
b110110 =
b110101 %
b110101 5
b110101 <
1!
#2020
0!
#2025
b110111 =
b110110 %
b110110 5
b110110 <
b110110 1
b10110010111 4
b1000111 2
1!
#2030
0!
#2035
b1000110 2
b110111 1
b10111001101 4
b111000 =
b110111 %
b110111 5
b110111 <
1!
#2040
0!
#2045
b111001 =
b111000 %
b111000 5
b111000 <
b111000 1
b11000000100 4
b1000101 2
1!
#2050
0!
#2055
b1000100 2
b111001 1
b11000111100 4
b111010 =
b111001 %
b111001 5
b111001 <
1!
#2060
0!
#2065
b111011 =
b111010 %
b111010 5
b111010 <
b111010 1
b11001110101 4
b1000011 2
1!
#2070
0!
#2075
b1000010 2
b111011 1
b11010101111 4
b111100 =
b111011 %
b111011 5
b111011 <
1!
#2080
0!
#2085
b111101 =
b111100 %
b111100 5
b111100 <
b111100 1
b11011101010 4
b1000001 2
1!
#2090
0!
#2095
b1000000 2
b111101 1
b11100100110 4
b111110 =
b111101 %
b111101 5
b111101 <
1!
#2100
0!
#2105
b111111 =
b111110 %
b111110 5
b111110 <
b111110 1
b11101100011 4
b111111 2
1!
#2110
0!
#2115
b111110 2
b111111 1
b11110100001 4
b1000000 =
b111111 %
b111111 5
b111111 <
1!
#2120
0!
#2125
b1000001 =
b1000000 %
b1000000 5
b1000000 <
b1000000 1
b11111100000 4
b111101 2
1!
#2130
0!
#2135
b111100 2
b1000001 1
b100000100000 4
b1000010 =
b1000001 %
b1000001 5
b1000001 <
1!
#2140
0!
#2145
b1000011 =
b1000010 %
b1000010 5
b1000010 <
b1000010 1
b100001100001 4
b111011 2
1!
#2150
0!
#2155
b111010 2
b1000011 1
b100010100011 4
b1000100 =
b1000011 %
b1000011 5
b1000011 <
1!
#2160
0!
#2165
b1000101 =
b1000100 %
b1000100 5
b1000100 <
b1000100 1
b100011100110 4
b111001 2
1!
#2170
0!
#2175
b111000 2
b1000101 1
b100100101010 4
b1000110 =
b1000101 %
b1000101 5
b1000101 <
1!
#2180
0!
#2185
b1000111 =
b1000110 %
b1000110 5
b1000110 <
b1000110 1
b100101101111 4
b110111 2
1!
#2190
0!
#2195
b110110 2
b1000111 1
b100110110101 4
b1001000 =
b1000111 %
b1000111 5
b1000111 <
1!
#2200
0!
#2205
b1001001 =
b1001000 %
b1001000 5
b1001000 <
b1001000 1
b100111111100 4
b110101 2
1!
#2210
0!
#2215
b110100 2
b1001001 1
b101001000100 4
b1001010 =
b1001001 %
b1001001 5
b1001001 <
1!
#2220
0!
#2225
b1001011 =
b1001010 %
b1001010 5
b1001010 <
b1001010 1
b101010001101 4
b110011 2
1!
#2230
0!
#2235
b110010 2
b1001011 1
b101011010111 4
b1001100 =
b1001011 %
b1001011 5
b1001011 <
1!
#2240
0!
#2245
b1001101 =
b1001100 %
b1001100 5
b1001100 <
b1001100 1
b101100100010 4
b110001 2
1!
#2250
0!
#2255
b110000 2
b1001101 1
b101101101110 4
b1001110 =
b1001101 %
b1001101 5
b1001101 <
1!
#2260
0!
#2265
b1001111 =
b1001110 %
b1001110 5
b1001110 <
b1001110 1
b101110111011 4
b101111 2
1!
#2270
0!
#2275
b101110 2
b1001111 1
b110000001001 4
b1010000 =
b1001111 %
b1001111 5
b1001111 <
1!
#2280
0!
#2285
b1010001 =
b1010000 %
b1010000 5
b1010000 <
b1010000 1
b110001011000 4
b101101 2
1!
#2290
0!
#2295
b101100 2
b1010001 1
b110010101000 4
b1010010 =
b1010001 %
b1010001 5
b1010001 <
1!
#2300
0!
#2305
b1010011 =
b1010010 %
b1010010 5
b1010010 <
b1010010 1
b110011111001 4
b101011 2
1!
#2310
0!
#2315
b101010 2
b1010011 1
b110101001011 4
b1010100 =
b1010011 %
b1010011 5
b1010011 <
1!
#2320
0!
#2325
b1010101 =
b1010100 %
b1010100 5
b1010100 <
b1010100 1
b110110011110 4
b101001 2
1!
#2330
0!
#2335
b101000 2
b1010101 1
b110111110010 4
b1010110 =
b1010101 %
b1010101 5
b1010101 <
1!
#2340
0!
#2345
b1010111 =
b1010110 %
b1010110 5
b1010110 <
b1010110 1
b111001000111 4
b100111 2
1!
#2350
0!
