veriloggen-develop/examples/ram_rtl/tmp.v


module test
(

);

  reg CLK;
  reg RST;

  main
  uut
  (
    .CLK(CLK),
    .RST(RST)
  );


  initial begin
    $dumpfile("uut.vcd");
    $dumpvars(0, uut, CLK, RST);
  end


  initial begin
    CLK = 0;
    forever begin
      #5 CLK = !CLK;
    end
  end


  initial begin
    RST = 0;
    #100;
    RST = 1;
    #100;
    RST = 0;
    #100000;
    $finish;
  end


endmodule



module main
(
  input CLK,
  input RST
);

  wire [14-1:0] myram_0_addr;
  wire [32-1:0] myram_0_rdata;
  wire [32-1:0] myram_0_wdata;
  wire myram_0_wenable;
  wire myram_0_enable;

  myram
  inst_myram
  (
    .CLK(CLK),
    .myram_0_addr(myram_0_addr),
    .myram_0_rdata(myram_0_rdata),
    .myram_0_wdata(myram_0_wdata),
    .myram_0_wenable(myram_0_wenable),
    .myram_0_enable(myram_0_enable)
  );

  reg [32-1:0] count;
  reg [32-1:0] sum;
  reg [32-1:0] addr;
  reg [32-1:0] fsm;
  localparam fsm_init = 0;
  assign myram_0_wdata = (fsm == 1)? count : 'hx;
  assign myram_0_wenable = (fsm == 1)? 1'd1 : 0;
  assign myram_0_addr = (fsm == 2)? addr : 
                        (fsm == 1)? addr : 'hx;
  assign myram_0_enable = (fsm == 2)? 1'd1 : 
                          (fsm == 1)? 1'd1 : 0;
  localparam _tmp_0 = 1;
  wire [_tmp_0-1:0] _tmp_1;
  assign _tmp_1 = fsm == 2;
  reg [_tmp_0-1:0] __tmp_1_1;
  reg [32-1:0] _d1_fsm;
  reg _fsm_cond_2_0_1;
  reg _fsm_cond_3_1_1;
  localparam fsm_1 = 1;
  localparam fsm_2 = 2;
  localparam fsm_3 = 3;
  localparam fsm_4 = 4;
  localparam fsm_5 = 5;

  always @(posedge CLK) begin
    if(RST) begin
      fsm <= fsm_init;
      _d1_fsm <= fsm_init;
      addr <= 0;
      count <= 0;
      sum <= 0;
      _fsm_cond_2_0_1 <= 0;
      _fsm_cond_3_1_1 <= 0;
    end else begin
      _d1_fsm <= fsm;
      case(_d1_fsm)
        fsm_2: begin
          if(_fsm_cond_2_0_1) begin
            $display("sum=%d", sum);
          end 
        end
        fsm_3: begin
          if(_fsm_cond_3_1_1) begin
            $display("sum=%d", sum);
          end 
        end
      endcase
      case(fsm)
        fsm_init: begin
          addr <= 0;
          count <= 0;
          sum <= 0;
          fsm <= fsm_1;
        end
        fsm_1: begin
          addr <= addr + 1;
          count <= count + 1;
          if(count == 15) begin
            addr <= 0;
            count <= 0;
          end 
          if(count == 15) begin
            fsm <= fsm_2;
          end 
        end
        fsm_2: begin
          addr <= addr + 1;
          count <= count + 1;
          if(__tmp_1_1) begin
            sum <= sum + myram_0_rdata;
          end 
          _fsm_cond_2_0_1 <= __tmp_1_1;
          if(count == 15) begin
            addr <= 0;
            count <= 0;
          end 
          if(count == 15) begin
            fsm <= fsm_3;
          end 
        end
        fsm_3: begin
          if(__tmp_1_1) begin
            sum <= sum + myram_0_rdata;
          end 
          _fsm_cond_3_1_1 <= __tmp_1_1;
          fsm <= fsm_4;
        end
        fsm_4: begin
          $display("expected_sum=%d", 120);
          fsm <= fsm_5;
        end
      endcase
    end
  end


  always @(posedge CLK) begin
    if(RST) begin
      __tmp_1_1 <= 0;
    end else begin
      __tmp_1_1 <= _tmp_1;
    end
  end


endmodule



module myram
(
  input CLK,
  input [14-1:0] myram_0_addr,
  output [32-1:0] myram_0_rdata,
  input [32-1:0] myram_0_wdata,
  input myram_0_wenable,
  input myram_0_enable
);

  reg [32-1:0] myram_0_rdata_out;
  assign myram_0_rdata = myram_0_rdata_out;
  reg [32-1:0] mem [0:16384-1];

  always @(posedge CLK) begin
    if(myram_0_enable) begin
      if(myram_0_wenable) begin
        mem[myram_0_addr] <= myram_0_wdata;
        myram_0_rdata_out <= myram_0_wdata;
      end else begin
        myram_0_rdata_out <= mem[myram_0_addr];
      end
    end 
  end


endmodule

veriloggen-develop/examples/ram_rtl/uut.vcd
$date
	Sat Jun 19 21:38:01 2021
$end
$version
	Icarus Verilog
$end
$timescale
	1s
$end
$scope module test $end
$scope module uut $end
$var wire 1 ! CLK $end
$var wire 1 " RST $end
$var wire 1 # myram_0_wenable $end
$var wire 32 $ myram_0_wdata [31:0] $end
$var wire 32 % myram_0_rdata [31:0] $end
$var wire 1 & myram_0_enable $end
$var wire 14 ' myram_0_addr [13:0] $end
$var wire 1 ( _tmp_1 $end
$var reg 1 ) __tmp_1_1 $end
$var reg 32 * _d1_fsm [31:0] $end
$var reg 1 + _fsm_cond_2_0_1 $end
$var reg 1 , _fsm_cond_3_1_1 $end
$var reg 32 - addr [31:0] $end
$var reg 32 . count [31:0] $end
$var reg 32 / fsm [31:0] $end
$var reg 32 0 sum [31:0] $end
$scope module inst_myram $end
$var wire 1 ! CLK $end
$var wire 14 1 myram_0_addr [13:0] $end
$var wire 1 & myram_0_enable $end
$var wire 32 2 myram_0_rdata [31:0] $end
$var wire 32 3 myram_0_wdata [31:0] $end
$var wire 1 # myram_0_wenable $end
$var reg 32 4 myram_0_rdata_out [31:0] $end
$upscope $end
$upscope $end
$upscope $end
$scope module test $end
$var reg 1 ! CLK $end
$upscope $end
$scope module test $end
$var reg 1 " RST $end
$upscope $end
$enddefinitions $end
#0
$dumpvars
bx 4
bx 3
bx 2
bx 1
bx 0
bx /
bx .
bx -
x,
x+
bx *
x)
x(
bx '
x&
bx %
bx $
x#
0"
0!
$end
#5
1!
#10
0!
#15
1!
#20
0!
#25
1!
#30
0!
#35
1!
#40
0!
#45
1!
#50
0!
#55
1!
#60
0!
#65
1!
#70
0!
#75
1!
#80
0!
#85
1!
#90
0!
#95
1!
#100
0!
1"
#105
0#
0&
0,
0+
b0 0
b0 .
b0 -
b0 *
0(
b0 /
0)
1!
#110
0!
#115
1!
#120
0!
#125
1!
#130
0!
#135
1!
#140
0!
#145
1!
#150
0!
#155
1!
#160
0!
#165
1!
#170
0!
#175
1!
#180
0!
#185
1!
#190
0!
#195
1!
#200
0!
0"
#205
b0 '
b0 1
1&
b0 $
b0 3
1#
b1 /
1!
#210
0!
#215
b1 '
b1 1
b1 $
b1 3
b1 .
b1 -
b1 *
b0 %
b0 2
b0 4
1!
#220
0!
#225
b10 '
b10 1
b10 $
b10 3
b1 %
b1 2
b1 4
b10 .
b10 -
1!
#230
0!
#235
b11 '
b11 1
b11 $
b11 3
b11 .
b11 -
b10 %
b10 2
b10 4
1!
#240
0!
#245
b100 '
b100 1
b100 $
b100 3
b11 %
b11 2
b11 4
b100 .
b100 -
1!
#250
0!
#255
b101 '
b101 1
b101 $
b101 3
b101 .
b101 -
b100 %
b100 2
b100 4
1!
#260
0!
#265
b110 '
b110 1
b110 $
b110 3
b101 %
b101 2
b101 4
b110 .
b110 -
1!
#270
0!
#275
b111 '
b111 1
b111 $
b111 3
b111 .
b111 -
b110 %
b110 2
b110 4
1!
#280
0!
#285
b1000 '
b1000 1
b1000 $
b1000 3
b111 %
b111 2
b111 4
b1000 .
b1000 -
1!
#290
0!
#295
b1001 '
b1001 1
b1001 $
b1001 3
b1001 .
b1001 -
b1000 %
b1000 2
b1000 4
1!
#300
0!
#305
b1010 '
b1010 1
b1010 $
b1010 3
b1001 %
b1001 2
b1001 4
b1010 .
b1010 -
1!
#310
0!
#315
b1011 '
b1011 1
b1011 $
b1011 3
b1011 .
b1011 -
b1010 %
b1010 2
b1010 4
1!
#320
0!
#325
b1100 '
b1100 1
b1100 $
b1100 3
b1011 %
b1011 2
b1011 4
b1100 .
b1100 -
1!
#330
0!
#335
b1101 '
b1101 1
b1101 $
b1101 3
b1101 .
b1101 -
b1100 %
b1100 2
b1100 4
1!
#340
0!
#345
b1110 '
b1110 1
b1110 $
b1110 3
b1101 %
b1101 2
b1101 4
b1110 .
b1110 -
1!
#350
0!
#355
b1111 '
b1111 1
b1111 $
b1111 3
b1111 .
b1111 -
b1110 %
b1110 2
b1110 4
1!
#360
0!
#365
b0 '
b0 1
0#
bx $
bx 3
b1111 %
b1111 2
b1111 4
1(
b10 /
b0 .
b0 -
1!
#370
0!
#375
b1 '
b1 1
1)
b1 .
b1 -
b10 *
b0 %
b0 2
b0 4
1!
#380
0!
#385
b10 '
b10 1
b1 %
b1 2
b1 4
1+
b10 .
b10 -
1!
#390
0!
#395
b11 '
b11 1
b1 0
b11 .
b11 -
b10 %
b10 2
b10 4
1!
#400
0!
#405
b100 '
b100 1
b11 %
b11 2
b11 4
b11 0
b100 .
b100 -
1!
#410
0!
#415
b101 '
b101 1
b110 0
b101 .
b101 -
b100 %
b100 2
b100 4
1!
#420
0!
#425
b110 '
b110 1
b101 %
b101 2
b101 4
b1010 0
b110 .
b110 -
1!
#430
0!
#435
b111 '
b111 1
b1111 0
b111 .
b111 -
b110 %
b110 2
b110 4
1!
#440
0!
#445
b1000 '
b1000 1
b111 %
b111 2
b111 4
b10101 0
b1000 .
b1000 -
1!
#450
0!
#455
b1001 '
b1001 1
b11100 0
b1001 .
b1001 -
b1000 %
b1000 2
b1000 4
1!
#460
0!
#465
b1010 '
b1010 1
b1001 %
b1001 2
b1001 4
b100100 0
b1010 .
b1010 -
1!
#470
0!
#475
b1011 '
b1011 1
b101101 0
b1011 .
b1011 -
b1010 %
b1010 2
b1010 4
1!
#480
0!
#485
b1100 '
b1100 1
b1011 %
b1011 2
b1011 4
b110111 0
b1100 .
b1100 -
1!
#490
0!
#495
b1101 '
b1101 1
b1000010 0
b1101 .
b1101 -
b1100 %
b1100 2
b1100 4
1!
#500
0!
#505
b1110 '
b1110 1
b1101 %
b1101 2
b1101 4
b1001110 0
b1110 .
b1110 -
1!
#510
0!
#515
b1111 '
b1111 1
b1011011 0
b1111 .
b1111 -
b1110 %
b1110 2
b1110 4
1!
#520
0!
#525
bx '
bx 1
0&
b1111 %
b1111 2
b1111 4
0(
b11 /
b1101001 0
b0 .
b0 -
1!
#530
0!
#535
0)
b100 /
1,
b1111000 0
b11 *
1!
#540
0!
#545
b101 /
b100 *
1!
#550
0!
#555
b101 *
1!
